dfauditor/__init__.py
dfauditor/app_logger.py
dfauditor/auditor.py
dfauditor/extractor.py
dfauditor/measures.py
dfauditor/metrics.py
dfauditor/response.py
dfauditor-0.0.4.data/data/LICENSE
dfauditor-0.0.4.dist-info/LICENSE
dfauditor-0.0.4.dist-info/METADATA
dfauditor-0.0.4.dist-info/WHEEL
dfauditor-0.0.4.dist-info/top_level.txt
dfauditor-0.0.4.dist-info/RECORD
