Metadata-Version: 2.1
Name: dfauditor
Version: 0.0.4
Summary: A dataframe auditor that extracts descriptive statistics from dataframe columns
Home-page: https://gitlab.com/spatialedge/ml-engineering/dataframe-auditor
Author: Jacques du Toit, Carl du Plessis
Author-email: 
License: UNKNOWN
Platform: UNKNOWN
Classifier: Environment :: Console
Classifier: Intended Audience :: Developers
Classifier: Programming Language :: Python :: 3
Classifier: Topic :: Scientific/Engineering :: Information Analysis
Classifier: Topic :: Utilities
Requires-Dist: certifi (>=2020.6.20)
Requires-Dist: chardet (>=3.0.4)
Requires-Dist: coverage (>=5.2)
Requires-Dist: coveralls (>=2.1.1)
Requires-Dist: docopt (>=0.6.2)
Requires-Dist: idna (>=2.10)
Requires-Dist: numpy (>=1.19.0)
Requires-Dist: pandas (>=1.0.5)
Requires-Dist: psutil (>=5.7.2)
Requires-Dist: python-dateutil (>=2.8.1)
Requires-Dist: pytz (>=2020.1)
Requires-Dist: requests (>=2.24.0)
Requires-Dist: scipy (>=1.5.1)
Requires-Dist: six (>=1.15.0)
Requires-Dist: urllib3 (>=1.25.9)
